{
  "chapters": {
    "1": {
      "pendingViews": 0,
      "lastIncrement": "2025-12-25T19:52:12.605Z",
      "lastUpdate": "2025-12-27T00:11:16+07:00"
    },
    "2.1": {
      "pendingViews": 0,
      "lastIncrement": "2025-12-25T20:01:48.733Z",
      "lastUpdate": "2025-12-27T00:11:16+07:00"
    },
    "2.2": {
      "pendingViews": 0,
      "lastIncrement": "2025-12-25T20:06:19.114Z",
      "lastUpdate": "2025-12-27T00:11:16+07:00"
    },
    "3.1": {
      "pendingViews": 0,
      "lastIncrement": "2025-12-25T20:13:14.566Z",
      "lastUpdate": "2025-12-27T00:11:16+07:00"
    },
    "3.2": {
      "pendingViews": 0,
      "lastIncrement": "2025-12-25T20:15:48.691Z",
      "lastUpdate": "2025-12-27T00:11:16+07:00"
    },
    "4.1": {
      "pendingViews": 1,
      "lastIncrement": "2025-12-26T18:14:42.464Z",
      "lastUpdate": "2025-12-27T00:11:16+07:00"
    },
    "4.2": {
      "pendingViews": 2,
      "lastIncrement": "2025-12-27T00:15:36.805Z",
      "lastUpdate": "2025-12-27T00:11:16+07:00"
    },
    "5.1": {
      "pendingViews": 3,
      "lastIncrement": "2025-12-27T04:25:03.577Z",
      "lastUpdate": "2025-12-27T00:11:16+07:00"
    },
    "5.2": {
      "pendingViews": 1,
      "lastIncrement": "2025-12-27T00:19:18.136Z",
      "lastUpdate": "2025-12-26T00:11:23+07:00"
    },
    "6.1": {
      "pendingViews": 1,
      "lastIncrement": "2025-12-27T00:20:18.652Z",
      "lastUpdate": "2025-12-27T00:11:16+07:00"
    },
    "6.2": {
      "pendingViews": 2,
      "lastIncrement": "2025-12-27T04:38:20.796Z",
      "lastUpdate": "2025-12-26T00:11:23+07:00"
    },
    "7.1": {
      "pendingViews": 2,
      "lastIncrement": "2025-12-27T04:40:09.319Z",
      "lastUpdate": "2025-12-27T00:11:16+07:00"
    },
    "7.2": {
      "pendingViews": 2,
      "lastIncrement": "2025-12-27T04:44:40.773Z",
      "lastUpdate": "2025-12-26T00:11:23+07:00"
    },
    "8.1": {
      "pendingViews": 1,
      "lastIncrement": "2025-12-27T00:13:50.013Z",
      "lastUpdate": "2025-12-26T00:11:23+07:00"
    },
    "8.2": {
      "pendingViews": 6,
      "lastIncrement": "2025-12-27T04:37:45.810Z",
      "lastUpdate": "2025-12-27T00:11:16+07:00"
    },
    "9.1": {
      "pendingViews": 8,
      "lastIncrement": "2025-12-27T04:26:06.235Z",
      "lastUpdate": "2025-12-27T00:11:16+07:00"
    }
  },
  "lastUpdated": "2025-12-27T00:11:16+07:00"
}