{
  "chapters": {
    "1": {
      "pendingViews": 4,
      "lastIncrement": "2025-12-24T04:01:51.738Z",
      "lastUpdate": "2025-12-24T00:13:35+07:00"
    },
    "2.1": {
      "pendingViews": 4,
      "lastIncrement": "2025-12-24T03:57:35.051Z",
      "lastUpdate": "2025-12-24T00:13:35+07:00"
    },
    "2.2": {
      "pendingViews": 2,
      "lastIncrement": "2025-12-24T03:09:03.192Z",
      "lastUpdate": "2025-12-24T00:13:35+07:00"
    },
    "3.1": {
      "pendingViews": 1,
      "lastIncrement": "2025-12-24T03:19:00.245Z",
      "lastUpdate": "2025-12-24T00:13:35+07:00"
    },
    "3.2": {
      "pendingViews": 1,
      "lastIncrement": "2025-12-24T03:20:50.658Z",
      "lastUpdate": "2025-12-24T00:13:35+07:00"
    },
    "4.1": {
      "pendingViews": 1,
      "lastIncrement": "2025-12-24T03:22:13.375Z",
      "lastUpdate": "2025-12-24T00:13:35+07:00"
    },
    "4.2": {
      "pendingViews": 1,
      "lastIncrement": "2025-12-24T03:23:20.134Z",
      "lastUpdate": "2025-12-24T00:13:35+07:00"
    },
    "5.1": {
      "pendingViews": 1,
      "lastIncrement": "2025-12-24T03:27:36.512Z",
      "lastUpdate": "2025-12-24T00:13:35+07:00"
    },
    "5.2": {
      "pendingViews": 1,
      "lastIncrement": "2025-12-24T03:29:06.717Z",
      "lastUpdate": "2025-12-24T00:13:35+07:00"
    },
    "6.1": {
      "pendingViews": 1,
      "lastIncrement": "2025-12-24T03:31:43.021Z",
      "lastUpdate": "2025-12-24T00:13:35+07:00"
    },
    "6.2": {
      "pendingViews": 1,
      "lastIncrement": "2025-12-24T03:33:04.131Z",
      "lastUpdate": "2025-12-24T00:13:35+07:00"
    },
    "7.1": {
      "pendingViews": 1,
      "lastIncrement": "2025-12-24T03:36:30.675Z",
      "lastUpdate": "2025-12-24T00:13:35+07:00"
    },
    "7.2": {
      "pendingViews": 2,
      "lastIncrement": "2025-12-24T03:38:18.560Z",
      "lastUpdate": "2025-12-24T00:13:35+07:00"
    },
    "8.1": {
      "pendingViews": 1,
      "lastIncrement": "2025-12-24T01:35:56.943Z",
      "lastUpdate": "2025-12-24T00:13:35+07:00"
    },
    "8.2": {
      "pendingViews": 1,
      "lastIncrement": "2025-12-24T01:37:29.597Z",
      "lastUpdate": "2025-12-24T00:13:35+07:00"
    },
    "9.1": {
      "pendingViews": 3,
      "lastIncrement": "2025-12-24T03:37:35.697Z",
      "lastUpdate": "2025-12-24T00:13:35+07:00"
    }
  },
  "lastUpdated": "2025-12-24T00:13:35+07:00"
}